COPYING
MANIFEST.in
README.rst
buildout.cfg
develop.cfg
pyproject.toml
requirements.txt
setup.py
version.txt
bob/__init__.py
bob.ip.facedetect.egg-info/PKG-INFO
bob.ip.facedetect.egg-info/SOURCES.txt
bob.ip.facedetect.egg-info/dependency_links.txt
bob.ip.facedetect.egg-info/entry_points.txt
bob.ip.facedetect.egg-info/not-zip-safe
bob.ip.facedetect.egg-info/requires.txt
bob.ip.facedetect.egg-info/top_level.txt
bob/ip/__init__.py
bob/ip/facedetect/MCT_cascade.hdf5
bob/ip/facedetect/__init__.py
bob/ip/facedetect/bounding_box.cpp
bob/ip/facedetect/detect.py
bob/ip/facedetect/feature_extractor.cpp
bob/ip/facedetect/main.cpp
bob/ip/facedetect/main.h
bob/ip/facedetect/mtcnn.py
bob/ip/facedetect/tinyface.py
bob/ip/facedetect/version.cpp
bob/ip/facedetect/cpp/boundingbox.cpp
bob/ip/facedetect/cpp/features.cpp
bob/ip/facedetect/cpp/features.h
bob/ip/facedetect/data/boxes.hdf5
bob/ip/facedetect/data/detections.hdf5
bob/ip/facedetect/data/extractor.hdf5
bob/ip/facedetect/data/mtcnn.pb
bob/ip/facedetect/data/test_image_multi_face.png
bob/ip/facedetect/data/testimage.jpg
bob/ip/facedetect/data/testimage.pos
bob/ip/facedetect/data/training.hdf5
bob/ip/facedetect/detector/__init__.py
bob/ip/facedetect/detector/cascade.py
bob/ip/facedetect/detector/sampler.py
bob/ip/facedetect/script/__init__.py
bob/ip/facedetect/script/collect_training_data.py
bob/ip/facedetect/script/detect_faces.py
bob/ip/facedetect/script/evaluate.py
bob/ip/facedetect/script/extract_training_features.py
bob/ip/facedetect/script/plot_froc.py
bob/ip/facedetect/script/train_detector.py
bob/ip/facedetect/script/validate_detector.py
bob/ip/facedetect/tests/__init__.py
bob/ip/facedetect/tests/test_cpp.py
bob/ip/facedetect/tests/test_features.py
bob/ip/facedetect/tests/test_mtcnn.py
bob/ip/facedetect/tests/test_sampler.py
bob/ip/facedetect/tests/test_scripts.py
bob/ip/facedetect/tests/test_tinyface.py
bob/ip/facedetect/tests/test_training.py
bob/ip/facedetect/tests/utils.py
bob/ip/facedetect/train/Bootstrap.py
bob/ip/facedetect/train/TrainingSet.py
bob/ip/facedetect/train/__init__.py
bob/ip/facedetect/train/annotations.py
bob/ip/facedetect/train/utils.py
bob/ip/flandmark/__init__.py
bob/ip/flandmark/flandmark.cpp
bob/ip/flandmark/main.cpp
bob/ip/flandmark/test.py
bob/ip/flandmark/version.cpp
