Metadata-Version: 2.1
Name: bob.ip.facedetect
Version: 4.1.0
Summary: Face detection using boosted LBP features
Home-page: http://gitlab.idiap.ch/bob/bob.ip.facedetect
Author: Manuel Guenther
Author-email: manuel.guenther@idiap.ch
License: GPLv3
Keywords: bob,face detection
Platform: UNKNOWN
Classifier: Framework :: Bob
Classifier: Development Status :: 4 - Beta
Classifier: Intended Audience :: Developers
Classifier: License :: OSI Approved :: BSD License
Classifier: Natural Language :: English
Classifier: Programming Language :: Python
Classifier: Programming Language :: Python :: 3
Classifier: Topic :: Software Development :: Libraries :: Python Modules
Classifier: Environment :: Plugins
License-File: COPYING
